datastack/__init__.py
datastack/cli.py
datastack/logger.py
datastack/plugin/chart.py
datastack/runtime/__init__.py
datastack/runtime/runtime.py
datastack/runtime/session_manager.py
datastack/runtime/test_app.py
datastack/server/__init__.py
datastack/server/auth.py
datastack/server/caching.py
datastack/server/ds_class.py
datastack/server/enovix_test_app.py
datastack/server/enovix_test_app1.py
datastack/server/server.py
datastack/server/utils.py
datastack/static/3rdpartylicenses.txt
datastack/static/app.json
datastack/static/favicon.ico
datastack/static/index.html
datastack/static/main.020c9f41fa4720ff.js
datastack/static/main.11afc696ed4dbab6.js
datastack/static/main.13d16d16594775cf.js
datastack/static/main.2d2232b5c1b27dd9.js
datastack/static/main.430969208671e0c4.js
datastack/static/main.57f734ac51808a6f.js
datastack/static/main.81df02d8749804cb.js
datastack/static/main.84d83bf890e6ed0e.js
datastack/static/main.af4e457d32d50c30.js
datastack/static/main.d599b004010ee349.js
datastack/static/main.e789ec36a911277f.js
datastack/static/polyfills.dab51ea5492118af.js
datastack/static/runtime.aaedba49815d2ab0.js
datastack/static/styles.e13040b928f048c1.css
datastack1-0.0.2.data/data/static/3rdpartylicenses.txt
datastack1-0.0.2.data/data/static/app.json
datastack1-0.0.2.data/data/static/favicon.ico
datastack1-0.0.2.data/data/static/index.html
datastack1-0.0.2.data/data/static/main.020c9f41fa4720ff.js
datastack1-0.0.2.data/data/static/main.11afc696ed4dbab6.js
datastack1-0.0.2.data/data/static/main.13d16d16594775cf.js
datastack1-0.0.2.data/data/static/main.2d2232b5c1b27dd9.js
datastack1-0.0.2.data/data/static/main.430969208671e0c4.js
datastack1-0.0.2.data/data/static/main.57f734ac51808a6f.js
datastack1-0.0.2.data/data/static/main.81df02d8749804cb.js
datastack1-0.0.2.data/data/static/main.84d83bf890e6ed0e.js
datastack1-0.0.2.data/data/static/main.af4e457d32d50c30.js
datastack1-0.0.2.data/data/static/main.d599b004010ee349.js
datastack1-0.0.2.dist-info/LICENSE
datastack1-0.0.2.dist-info/METADATA
datastack1-0.0.2.dist-info/WHEEL
datastack1-0.0.2.dist-info/entry_points.txt
datastack1-0.0.2.dist-info/top_level.txt
datastack1-0.0.2.dist-info/RECORD
