Metadata-Version: 2.1
Name: datastack1
Version: 0.0.2
Summary: Tool to build data apps on the fly
Author: Vishal Vora, Mayur Pokiya, Karan Doshi
License-File: LICENSE
Requires-Dist: click ==8.1.3
Requires-Dist: Flask ==2.2.2
Requires-Dist: Flask-Cors ==3.0.10
Requires-Dist: GitPython ==3.1.31
Requires-Dist: numpy
Requires-Dist: pandas
Requires-Dist: plotly ==5.14.0
Requires-Dist: requests ==2.28.1
Requires-Dist: sphinx-rtd-theme
